hew/__init__.py
hew-0.6.0.dist-info/METADATA
hew-0.6.0.dist-info/WHEEL
hew-0.6.0.dist-info/entry_points.txt
hew-0.6.0.dist-info/licenses/LICENSE
hew-0.6.0.dist-info/RECORD
