Metadata-Version: 2.4
Name: hew
Version: 0.6.0
Summary: Hew is a specification and reference implementations to compile repository changelogs into release notes and other forms of documentation.
Project-URL: Homepage, https://log.hew.ing
Project-URL: Issues, https://codeberg.org/hew/python
Project-URL: Source, https://codeberg.org/hew/python
Project-URL: Changelog, https://codeberg.org/hew/python/releases
Author-email: Tyler Langlois <tyler+pypi@langlois.to>
License-Expression: AGPL-3.0-or-later
License-File: LICENSE
Keywords: changelog,documentation,git,release-notes
Classifier: License :: OSI Approved :: GNU Affero General Public License v3 or later (AGPLv3+)
Classifier: Operating System :: OS Independent
Classifier: Programming Language :: Python :: 3 :: Only
Classifier: Programming Language :: Python :: 3.11
Classifier: Programming Language :: Python :: 3.12
Classifier: Programming Language :: Python :: 3.13
Requires-Python: >=3.11
Requires-Dist: gitpython>=3.1.45
Requires-Dist: packaging>=25.0
Requires-Dist: python-magic>=0.4.27
Provides-Extra: frontmatter
Requires-Dist: python-frontmatter>=1.1.0; extra == 'frontmatter'
Provides-Extra: polyglot
Requires-Dist: pandoc>=2.4; extra == 'polyglot'
